{
  "updatedAt": "2026-03-31T19:44:36Z",
  "workspaceId": "ws-default",
  "overallHealth": "ok",
  "monitorRunId": "23816177050",
  "triggerEvent": "schedule",
  "autoDispatched": "",
  "components": {
    "agent": {
      "version": "source-change",
      "deployedAt": "2026-03-30T16:42:43Z",
      "deployRunId": "23755765756",
      "ciGateResult": "success",
      "gateDecision": "pass",
      "ciMonitorResult": "success",
      "ciMonitorAt": "2026-03-30T16:43:07Z",
      "stage": "idle",
      "health": "ok",
      "actionTaken": "none",
      "deployAge": "1621min"
    },
    "controller": {
      "version": "3.7.4",
      "deployedAt": "2026-03-31T17:39:33Z",
      "deployRunId": "23810562081",
      "ciGateResult": "success",
      "gateDecision": "pass",
      "ciMonitorResult": "success",
      "ciMonitorAt": "2026-03-31T17:39:57Z",
      "stage": "complete",
      "health": "ok",
      "actionTaken": "none",
      "deployAge": "125min"
    }
  }
}
